MANIFEST.in
README.md
prophesy_write_config.py
setup.py
Prophesy.egg-info/PKG-INFO
Prophesy.egg-info/SOURCES.txt
Prophesy.egg-info/dependency_links.txt
Prophesy.egg-info/requires.txt
Prophesy.egg-info/top_level.txt
prophesy/__init__.py
prophesy/_version.py
prophesy/config.py
prophesy/util.py
prophesy/adapter/__init__.py
prophesy/adapter/gurobipy.py
prophesy/adapter/pycarl.py
prophesy/adapter/stormpy.py
prophesy/data/__init__.py
prophesy/data/constant.py
prophesy/data/constraint.py
prophesy/data/hyperrectangle.py
prophesy/data/interval.py
prophesy/data/model_type.py
prophesy/data/nice_approximation.py
prophesy/data/parameter.py
prophesy/data/point.py
prophesy/data/property.py
prophesy/data/range.py
prophesy/data/samples.py
prophesy/exceptions/__init__.py
prophesy/exceptions/configuration_error.py
prophesy/exceptions/dimension_not_supported_error.py
prophesy/exceptions/module_error.py
prophesy/exceptions/not_enough_information_error.py
prophesy/exceptions/unsupported_model.py
prophesy/input/__init__.py
prophesy/input/modelfile.py
prophesy/input/pctlfile.py
prophesy/input/problem_description.py
prophesy/input/samplefile.py
prophesy/input/solutionfunctionfile.py
prophesy/modelcheckers/__init__.py
prophesy/modelcheckers/param.py
prophesy/modelcheckers/pmc.py
prophesy/modelcheckers/ppmc.py
prophesy/modelcheckers/prism.py
prophesy/modelcheckers/storm.py
prophesy/modelcheckers/stormpy.py
prophesy/modelrepair/__init__.py
prophesy/modelrepair/repairer.py
prophesy/optimisation/heuristic_search.py
prophesy/optimisation/pla_based_search.py
prophesy/optimisation/pla_region_optimiser.py
prophesy/optimisation/qcqp.py
prophesy/optimisation/simple_binary_search.py
prophesy/output/__init__.py
prophesy/output/plot.py
prophesy/regions/__init__.py
prophesy/regions/generation_record.py
prophesy/regions/region_checker.py
prophesy/regions/region_etrchecker.py
prophesy/regions/region_generation.py
prophesy/regions/region_icpchecker.py
prophesy/regions/region_monochecker.py
prophesy/regions/region_plachecker.py
prophesy/regions/region_quads.py
prophesy/regions/region_smtchecker.py
prophesy/regions/region_solutionfunctionchecker.py
